<annotation>
  <folder>images</folder>
  <filename>03b33081891bc8c2.jpg</filename>
  <path>horse/images/03b33081891bc8c2.jpg</path>
  <source>
    <database>OpenImages</database>
  </source>
  <size>
    <width>1024</width>
    <height>681</height>
    <depth>3</depth>
  </size>
  <segmented>0</segmented>
  <object>
    <name>horse</name>
    <pose>Unspecified</pose>
    <truncated>0</truncated>
    <difficult>0</difficult>
    <bndbox>
      <xmin>202</xmin>
      <xmax>474</xmax>
      <ymin>230</ymin>
      <ymax>533</ymax>
    </bndbox>
  </object>
  <object>
    <name>horse</name>
    <pose>Unspecified</pose>
    <truncated>0</truncated>
    <difficult>0</difficult>
    <bndbox>
      <xmin>474</xmin>
      <xmax>926</xmax>
      <ymin>195</ymin>
      <ymax>536</ymax>
    </bndbox>
  </object>
</annotation>
