<annotation>
  <folder>images</folder>
  <filename>7edf1639853804b7.jpg</filename>
  <path>horse/images/7edf1639853804b7.jpg</path>
  <source>
    <database>OpenImages</database>
  </source>
  <size>
    <width>1024</width>
    <height>683</height>
    <depth>3</depth>
  </size>
  <segmented>0</segmented>
  <object>
    <name>horse</name>
    <pose>Unspecified</pose>
    <truncated>0</truncated>
    <difficult>0</difficult>
    <bndbox>
      <xmin>472</xmin>
      <xmax>997</xmax>
      <ymin>190</ymin>
      <ymax>676</ymax>
    </bndbox>
  </object>
</annotation>
