<annotation>
  <folder>images</folder>
  <filename>a9f2114462511655.jpg</filename>
  <path>horse/images/a9f2114462511655.jpg</path>
  <source>
    <database>OpenImages</database>
  </source>
  <size>
    <width>1024</width>
    <height>518</height>
    <depth>3</depth>
  </size>
  <segmented>0</segmented>
  <object>
    <name>horse</name>
    <pose>Unspecified</pose>
    <truncated>0</truncated>
    <difficult>0</difficult>
    <bndbox>
      <xmin>159</xmin>
      <xmax>559</xmax>
      <ymin>257</ymin>
      <ymax>480</ymax>
    </bndbox>
  </object>
</annotation>
