<annotation>
  <folder>images</folder>
  <filename>cec3f954a895eb2d.jpg</filename>
  <path>horse/images/cec3f954a895eb2d.jpg</path>
  <source>
    <database>OpenImages</database>
  </source>
  <size>
    <width>1024</width>
    <height>860</height>
    <depth>3</depth>
  </size>
  <segmented>0</segmented>
  <object>
    <name>horse</name>
    <pose>Unspecified</pose>
    <truncated>0</truncated>
    <difficult>0</difficult>
    <bndbox>
      <xmin>97</xmin>
      <xmax>357</xmax>
      <ymin>342</ymin>
      <ymax>850</ymax>
    </bndbox>
  </object>
</annotation>
