<annotation>
  <folder>images</folder>
  <filename>da3e20e8e44f8899.jpg</filename>
  <path>horse/images/da3e20e8e44f8899.jpg</path>
  <source>
    <database>OpenImages</database>
  </source>
  <size>
    <width>1024</width>
    <height>683</height>
    <depth>3</depth>
  </size>
  <segmented>0</segmented>
  <object>
    <name>horse</name>
    <pose>Unspecified</pose>
    <truncated>0</truncated>
    <difficult>0</difficult>
    <bndbox>
      <xmin>145</xmin>
      <xmax>574</xmax>
      <ymin>132</ymin>
      <ymax>682</ymax>
    </bndbox>
  </object>
</annotation>
