<annotation>
  <folder>images</folder>
  <filename>f7ba616248b5f13e.jpg</filename>
  <path>horse/images/f7ba616248b5f13e.jpg</path>
  <source>
    <database>OpenImages</database>
  </source>
  <size>
    <width>1024</width>
    <height>768</height>
    <depth>3</depth>
  </size>
  <segmented>0</segmented>
  <object>
    <name>horse</name>
    <pose>Unspecified</pose>
    <truncated>0</truncated>
    <difficult>0</difficult>
    <bndbox>
      <xmin>462</xmin>
      <xmax>680</xmax>
      <ymin>312</ymin>
      <ymax>713</ymax>
    </bndbox>
  </object>
</annotation>
