<annotation>
  <folder>images</folder>
  <filename>425b6ce17c4f47c5.jpg</filename>
  <path>sheep/images/425b6ce17c4f47c5.jpg</path>
  <source>
    <database>OpenImages</database>
  </source>
  <size>
    <width>1024</width>
    <height>768</height>
    <depth>3</depth>
  </size>
  <segmented>0</segmented>
  <object>
    <name>sheep</name>
    <pose>Unspecified</pose>
    <truncated>0</truncated>
    <difficult>0</difficult>
    <bndbox>
      <xmin>130</xmin>
      <xmax>217</xmax>
      <ymin>190</ymin>
      <ymax>256</ymax>
    </bndbox>
  </object>
  <object>
    <name>sheep</name>
    <pose>Unspecified</pose>
    <truncated>0</truncated>
    <difficult>0</difficult>
    <bndbox>
      <xmin>277</xmin>
      <xmax>524</xmax>
      <ymin>380</ymin>
      <ymax>599</ymax>
    </bndbox>
  </object>
  <object>
    <name>sheep</name>
    <pose>Unspecified</pose>
    <truncated>0</truncated>
    <difficult>0</difficult>
    <bndbox>
      <xmin>602</xmin>
      <xmax>673</xmax>
      <ymin>240</ymin>
      <ymax>320</ymax>
    </bndbox>
  </object>
  <object>
    <name>sheep</name>
    <pose>Unspecified</pose>
    <truncated>0</truncated>
    <difficult>0</difficult>
    <bndbox>
      <xmin>634</xmin>
      <xmax>784</xmax>
      <ymin>298</ymin>
      <ymax>478</ymax>
    </bndbox>
  </object>
</annotation>
