<annotation>
  <folder>images</folder>
  <filename>9b175abf23f4b15a.jpg</filename>
  <path>sheep/images/9b175abf23f4b15a.jpg</path>
  <source>
    <database>OpenImages</database>
  </source>
  <size>
    <width>1024</width>
    <height>727</height>
    <depth>3</depth>
  </size>
  <segmented>0</segmented>
  <object>
    <name>sheep</name>
    <pose>Unspecified</pose>
    <truncated>0</truncated>
    <difficult>0</difficult>
    <bndbox>
      <xmin>10</xmin>
      <xmax>39</xmax>
      <ymin>575</ymin>
      <ymax>593</ymax>
    </bndbox>
  </object>
  <object>
    <name>sheep</name>
    <pose>Unspecified</pose>
    <truncated>0</truncated>
    <difficult>0</difficult>
    <bndbox>
      <xmin>12</xmin>
      <xmax>26</xmax>
      <ymin>552</ymin>
      <ymax>564</ymax>
    </bndbox>
  </object>
  <object>
    <name>sheep</name>
    <pose>Unspecified</pose>
    <truncated>0</truncated>
    <difficult>0</difficult>
    <bndbox>
      <xmin>48</xmin>
      <xmax>53</xmax>
      <ymin>549</ymin>
      <ymax>557</ymax>
    </bndbox>
  </object>
  <object>
    <name>sheep</name>
    <pose>Unspecified</pose>
    <truncated>0</truncated>
    <difficult>0</difficult>
    <bndbox>
      <xmin>165</xmin>
      <xmax>172</xmax>
      <ymin>552</ymin>
      <ymax>557</ymax>
    </bndbox>
  </object>
  <object>
    <name>sheep</name>
    <pose>Unspecified</pose>
    <truncated>0</truncated>
    <difficult>0</difficult>
    <bndbox>
      <xmin>181</xmin>
      <xmax>183</xmax>
      <ymin>550</ymin>
      <ymax>562</ymax>
    </bndbox>
  </object>
  <object>
    <name>sheep</name>
    <pose>Unspecified</pose>
    <truncated>0</truncated>
    <difficult>0</difficult>
    <bndbox>
      <xmin>213</xmin>
      <xmax>222</xmax>
      <ymin>552</ymin>
      <ymax>557</ymax>
    </bndbox>
  </object>
  <object>
    <name>sheep</name>
    <pose>Unspecified</pose>
    <truncated>0</truncated>
    <difficult>0</difficult>
    <bndbox>
      <xmin>227</xmin>
      <xmax>236</xmax>
      <ymin>552</ymin>
      <ymax>559</ymax>
    </bndbox>
  </object>
  <object>
    <name>sheep</name>
    <pose>Unspecified</pose>
    <truncated>0</truncated>
    <difficult>0</difficult>
    <bndbox>
      <xmin>236</xmin>
      <xmax>270</xmax>
      <ymin>580</ymin>
      <ymax>605</ymax>
    </bndbox>
  </object>
  <object>
    <name>sheep</name>
    <pose>Unspecified</pose>
    <truncated>0</truncated>
    <difficult>0</difficult>
    <bndbox>
      <xmin>359</xmin>
      <xmax>374</xmax>
      <ymin>568</ymin>
      <ymax>577</ymax>
    </bndbox>
  </object>
  <object>
    <name>sheep</name>
    <pose>Unspecified</pose>
    <truncated>0</truncated>
    <difficult>0</difficult>
    <bndbox>
      <xmin>384</xmin>
      <xmax>394</xmax>
      <ymin>557</ymin>
      <ymax>562</ymax>
    </bndbox>
  </object>
  <object>
    <name>sheep</name>
    <pose>Unspecified</pose>
    <truncated>0</truncated>
    <difficult>0</difficult>
    <bndbox>
      <xmin>394</xmin>
      <xmax>407</xmax>
      <ymin>578</ymin>
      <ymax>586</ymax>
    </bndbox>
  </object>
  <object>
    <name>sheep</name>
    <pose>Unspecified</pose>
    <truncated>0</truncated>
    <difficult>0</difficult>
    <bndbox>
      <xmin>410</xmin>
      <xmax>418</xmax>
      <ymin>579</ymin>
      <ymax>587</ymax>
    </bndbox>
  </object>
  <object>
    <name>sheep</name>
    <pose>Unspecified</pose>
    <truncated>0</truncated>
    <difficult>0</difficult>
    <bndbox>
      <xmin>444</xmin>
      <xmax>456</xmax>
      <ymin>566</ymin>
      <ymax>571</ymax>
    </bndbox>
  </object>
  <object>
    <name>sheep</name>
    <pose>Unspecified</pose>
    <truncated>0</truncated>
    <difficult>0</difficult>
    <bndbox>
      <xmin>488</xmin>
      <xmax>501</xmax>
      <ymin>559</ymin>
      <ymax>566</ymax>
    </bndbox>
  </object>
  <object>
    <name>sheep</name>
    <pose>Unspecified</pose>
    <truncated>0</truncated>
    <difficult>0</difficult>
    <bndbox>
      <xmin>514</xmin>
      <xmax>520</xmax>
      <ymin>558</ymin>
      <ymax>565</ymax>
    </bndbox>
  </object>
  <object>
    <name>sheep</name>
    <pose>Unspecified</pose>
    <truncated>0</truncated>
    <difficult>0</difficult>
    <bndbox>
      <xmin>563</xmin>
      <xmax>574</xmax>
      <ymin>564</ymin>
      <ymax>575</ymax>
    </bndbox>
  </object>
  <object>
    <name>sheep</name>
    <pose>Unspecified</pose>
    <truncated>0</truncated>
    <difficult>0</difficult>
    <bndbox>
      <xmin>577</xmin>
      <xmax>590</xmax>
      <ymin>561</ymin>
      <ymax>575</ymax>
    </bndbox>
  </object>
  <object>
    <name>sheep</name>
    <pose>Unspecified</pose>
    <truncated>0</truncated>
    <difficult>0</difficult>
    <bndbox>
      <xmin>702</xmin>
      <xmax>715</xmax>
      <ymin>561</ymin>
      <ymax>578</ymax>
    </bndbox>
  </object>
  <object>
    <name>sheep</name>
    <pose>Unspecified</pose>
    <truncated>0</truncated>
    <difficult>0</difficult>
    <bndbox>
      <xmin>715</xmin>
      <xmax>723</xmax>
      <ymin>561</ymin>
      <ymax>570</ymax>
    </bndbox>
  </object>
  <object>
    <name>sheep</name>
    <pose>Unspecified</pose>
    <truncated>0</truncated>
    <difficult>0</difficult>
    <bndbox>
      <xmin>724</xmin>
      <xmax>729</xmax>
      <ymin>563</ymin>
      <ymax>568</ymax>
    </bndbox>
  </object>
  <object>
    <name>sheep</name>
    <pose>Unspecified</pose>
    <truncated>0</truncated>
    <difficult>0</difficult>
    <bndbox>
      <xmin>735</xmin>
      <xmax>758</xmax>
      <ymin>595</ymin>
      <ymax>620</ymax>
    </bndbox>
  </object>
  <object>
    <name>sheep</name>
    <pose>Unspecified</pose>
    <truncated>0</truncated>
    <difficult>0</difficult>
    <bndbox>
      <xmin>749</xmin>
      <xmax>755</xmax>
      <ymin>563</ymin>
      <ymax>571</ymax>
    </bndbox>
  </object>
  <object>
    <name>sheep</name>
    <pose>Unspecified</pose>
    <truncated>0</truncated>
    <difficult>0</difficult>
    <bndbox>
      <xmin>782</xmin>
      <xmax>804</xmax>
      <ymin>573</ymin>
      <ymax>591</ymax>
    </bndbox>
  </object>
  <object>
    <name>sheep</name>
    <pose>Unspecified</pose>
    <truncated>0</truncated>
    <difficult>0</difficult>
    <bndbox>
      <xmin>816</xmin>
      <xmax>829</xmax>
      <ymin>589</ymin>
      <ymax>602</ymax>
    </bndbox>
  </object>
  <object>
    <name>sheep</name>
    <pose>Unspecified</pose>
    <truncated>0</truncated>
    <difficult>0</difficult>
    <bndbox>
      <xmin>829</xmin>
      <xmax>837</xmax>
      <ymin>561</ymin>
      <ymax>568</ymax>
    </bndbox>
  </object>
  <object>
    <name>sheep</name>
    <pose>Unspecified</pose>
    <truncated>0</truncated>
    <difficult>0</difficult>
    <bndbox>
      <xmin>842</xmin>
      <xmax>858</xmax>
      <ymin>590</ymin>
      <ymax>604</ymax>
    </bndbox>
  </object>
  <object>
    <name>sheep</name>
    <pose>Unspecified</pose>
    <truncated>0</truncated>
    <difficult>0</difficult>
    <bndbox>
      <xmin>845</xmin>
      <xmax>854</xmax>
      <ymin>559</ymin>
      <ymax>570</ymax>
    </bndbox>
  </object>
  <object>
    <name>sheep</name>
    <pose>Unspecified</pose>
    <truncated>0</truncated>
    <difficult>0</difficult>
    <bndbox>
      <xmin>866</xmin>
      <xmax>878</xmax>
      <ymin>595</ymin>
      <ymax>607</ymax>
    </bndbox>
  </object>
</annotation>
