<annotation>
  <folder>images</folder>
  <filename>c16e4c1f49e1a0d6.jpg</filename>
  <path>sheep/images/c16e4c1f49e1a0d6.jpg</path>
  <source>
    <database>OpenImages</database>
  </source>
  <size>
    <width>1024</width>
    <height>768</height>
    <depth>3</depth>
  </size>
  <segmented>0</segmented>
  <object>
    <name>sheep</name>
    <pose>Unspecified</pose>
    <truncated>0</truncated>
    <difficult>0</difficult>
    <bndbox>
      <xmin>756</xmin>
      <xmax>803</xmax>
      <ymin>480</ymin>
      <ymax>520</ymax>
    </bndbox>
  </object>
  <object>
    <name>sheep</name>
    <pose>Unspecified</pose>
    <truncated>0</truncated>
    <difficult>0</difficult>
    <bndbox>
      <xmin>781</xmin>
      <xmax>816</xmax>
      <ymin>410</ymin>
      <ymax>441</ymax>
    </bndbox>
  </object>
  <object>
    <name>sheep</name>
    <pose>Unspecified</pose>
    <truncated>0</truncated>
    <difficult>0</difficult>
    <bndbox>
      <xmin>906</xmin>
      <xmax>930</xmax>
      <ymin>292</ymin>
      <ymax>311</ymax>
    </bndbox>
  </object>
  <object>
    <name>sheep</name>
    <pose>Unspecified</pose>
    <truncated>0</truncated>
    <difficult>0</difficult>
    <bndbox>
      <xmin>946</xmin>
      <xmax>963</xmax>
      <ymin>248</ymin>
      <ymax>266</ymax>
    </bndbox>
  </object>
  <object>
    <name>sheep</name>
    <pose>Unspecified</pose>
    <truncated>0</truncated>
    <difficult>0</difficult>
    <bndbox>
      <xmin>971</xmin>
      <xmax>999</xmax>
      <ymin>339</ymin>
      <ymax>360</ymax>
    </bndbox>
  </object>
  <object>
    <name>sheep</name>
    <pose>Unspecified</pose>
    <truncated>0</truncated>
    <difficult>0</difficult>
    <bndbox>
      <xmin>986</xmin>
      <xmax>1008</xmax>
      <ymin>296</ymin>
      <ymax>317</ymax>
    </bndbox>
  </object>
  <object>
    <name>sheep</name>
    <pose>Unspecified</pose>
    <truncated>0</truncated>
    <difficult>0</difficult>
    <bndbox>
      <xmin>990</xmin>
      <xmax>1007</xmax>
      <ymin>241</ymin>
      <ymax>263</ymax>
    </bndbox>
  </object>
</annotation>
